alpaca/__init__.py
alpaca/broker/__init__.py
alpaca/broker/client.py
alpaca/broker/enums.py
alpaca/broker/models/__init__.py
alpaca/broker/models/accounts.py
alpaca/broker/models/cip.py
alpaca/broker/models/documents.py
alpaca/broker/models/funding.py
alpaca/broker/models/journals.py
alpaca/broker/models/rebalancing.py
alpaca/broker/models/trading.py
alpaca/broker/requests.py
alpaca/common/__init__.py
alpaca/common/constants.py
alpaca/common/enums.py
alpaca/common/exceptions.py
alpaca/common/models.py
alpaca/common/requests.py
alpaca/common/rest.py
alpaca/common/types.py
alpaca/common/utils.py
alpaca/data/__init__.py
alpaca/data/enums.py
alpaca/data/historical/__init__.py
alpaca/data/historical/corporate_actions.py
alpaca/data/historical/crypto.py
alpaca/data/historical/news.py
alpaca/data/historical/option.py
alpaca/data/historical/screener.py
alpaca/data/historical/stock.py
alpaca/data/historical/utils.py
alpaca/data/live/__init__.py
alpaca/data/live/crypto.py
alpaca/data/live/news.py
alpaca/data/live/option.py
alpaca/data/live/stock.py
alpaca/data/live/websocket.py
alpaca/data/mappings.py
alpaca/data/models/__init__.py
alpaca/data/models/bars.py
alpaca/data/models/base.py
alpaca/data/models/corporate_actions.py
alpaca/data/models/news.py
alpaca/data/models/orderbooks.py
alpaca/data/models/quotes.py
alpaca/data/models/screener.py
alpaca/data/models/snapshots.py
alpaca/data/models/trades.py
alpaca/data/requests.py
alpaca/data/timeframe.py
alpaca/py.typed
alpaca/trading/__init__.py
alpaca/trading/client.py
alpaca/trading/enums.py
alpaca/trading/models.py
alpaca/trading/requests.py
alpaca/trading/stream.py
alpaca_py_nopandas-0.1.2.dist-info/LICENSE
alpaca_py_nopandas-0.1.2.dist-info/METADATA
alpaca_py_nopandas-0.1.2.dist-info/WHEEL
alpaca_py_nopandas-0.1.2.dist-info/RECORD
